asfpy/__init__.py
asfpy/aioldap.py
asfpy/clitools.py
asfpy/crypto.py
asfpy/daemon.py
asfpy/db.py
asfpy/justone.py
asfpy/ldapadmin.py
asfpy/messaging.py
asfpy/pubsub.py
asfpy/sqlite.py
asfpy/stopwatch.py
asfpy/syslog.py
asfpy/twatcher.py
asfpy/whoami.py
asfpy-0.56.dist-info/LICENSE
asfpy-0.56.dist-info/METADATA
asfpy-0.56.dist-info/WHEEL
asfpy-0.56.dist-info/RECORD
