Metadata-Version: 2.1
Name: asfpy
Version: 0.56
Summary: ASF Common Python Methods
Author: ASF Infrastructure
Author-email: users@infra.apache.org
Requires-Python: >=3.9.2,<4
Classifier: License :: OSI Approved :: Apache Software License
Classifier: Programming Language :: Python :: 3
Classifier: Programming Language :: Python :: 3.10
Classifier: Programming Language :: Python :: 3.11
Classifier: Programming Language :: Python :: 3.12
Provides-Extra: aioldap
Provides-Extra: ldap
Requires-Dist: aiohttp (>=3.10.5,<4.0.0)
Requires-Dist: bonsai (>=1.5.3,<2.0.0) ; extra == "aioldap"
Requires-Dist: cffi (>=1.17.1,<2.0.0)
Requires-Dist: cryptography (>=44.0.2,<45.0.0)
Requires-Dist: easydict (>=1.13,<2.0)
Requires-Dist: ezt (>=1.1,<2.0)
Requires-Dist: passlib (>=1.7.4,<2.0.0) ; extra == "ldap" or extra == "aioldap"
Requires-Dist: python-ldap (>=3.4.4,<4.0.0) ; extra == "ldap"
Requires-Dist: pyyaml (>=6.0.2,<7.0.0)
Requires-Dist: requests (>=2.32.3,<3.0.0)
Requires-Dist: watchfiles (>=1.0.0,<2.0.0)
